<?xml version='1.0' encoding='utf-8'?>
<linkGrp toDoc='suv-t555-t665-16-phoebe-20230922.zh.xml' fromDoc='suv-t555-t665-16-phoebe-20230922.bo.xml'>
<link type='1-0' xtargets='1:1;' status='man'/>
<link type='1-0' xtargets='2:1;' status='man'/>
<link type='1-1' xtargets='3:1;1:1' status='man'/>
<link type='1-1' xtargets='3:2;2:1' status='man'/>
<link type='1-1' xtargets='3:3;3:1' status='man'/>
<link type='1-1' xtargets='3:4;4:1' status='man'/>
<link type='1-1' xtargets='3:5;5:1' status='man'/>
<link type='1-1' xtargets='3:6;6:1' status='man'/>
<link type='1-1' xtargets='3:7;7:1' status='man'/>
<link type='1-1' xtargets='3:8;8:1' status='man'/>
<link type='1-1' xtargets='4:1;9:1' status='man'/>
<link type='1-1' xtargets='4:2;10:1' status='man'/>
<link type='1-1' xtargets='4:3;10:2' status='man'/>
<link type='1-1' xtargets='4:4;10:3' status='man'/>
<link type='1-1' xtargets='4:5;10:4' status='man'/>
<link type='1-1' xtargets='5:1;10:5' status='man'/>
<link type='1-1' xtargets='5:2;10:6' status='man'/>
<link type='1-1' xtargets='5:3;10:7' status='man'/>
<link type='1-1' xtargets='5:4;11:1' status='man'/>
<link type='1-1' xtargets='5:5;12:1' status='man'/>
<link type='1-1' xtargets='5:6;12:2' status='man'/>
<link type='1-1' xtargets='6:1;12:3' status='man'/>
<link type='1-1' xtargets='6:2;13:1' status='man'/>
<link type='1-1' xtargets='6:3;13:2' status='man'/>
<link type='1-1' xtargets='6:4;14:1' status='man'/>
<link type='1-1' xtargets='6:5;15:1' status='man'/>
<link type='1-1' xtargets='6:6;15:2' status='man'/>
<link type='1-1' xtargets='6:7;15:3' status='man'/>
<link type='1-1' xtargets='6:8;15:4' status='man'/>
<link type='1-1' xtargets='6:9;16:1' status='man'/>
<link type='1-1' xtargets='6:10;17:1' status='man'/>
<link type='1-1' xtargets='6:11;17:2' status='man'/>
<link type='1-1' xtargets='6:12;17:3' status='man'/>
<link type='1-1' xtargets='6:13;17:4' status='man'/>
<link type='1-1' xtargets='6:14;17:5' status='man'/>
<link type='1-1' xtargets='6:15;17:6' status='man'/>
<link type='1-1' xtargets='6:16;18:1' status='man'/>
<link type='1-1' xtargets='7:1;19:1' status='man'/>
<link type='1-1' xtargets='7:2;20:1' status='man'/>
<link type='1-1' xtargets='7:3;21:1' status='man'/>
<link type='1-1' xtargets='7:4;22:1' status='man'/>
<link type='1-1' xtargets='8:1;22:2' status='man'/>
<link type='1-1' xtargets='8:2;22:3' status='man'/>
<link type='1-1' xtargets='8:3;22:4' status='man'/>
<link type='1-1' xtargets='8:4;22:5' status='man'/>
<link type='1-1' xtargets='8:5;23:1' status='man'/>
<link type='1-1' xtargets='8:6;23:2' status='man'/>
<link type='1-1' xtargets='8:7;24:1' status='man'/>
<link type='1-1' xtargets='8:8;24:2' status='man'/>
<link type='1-1' xtargets='8:9;25:1' status='man'/>
<link type='1-1' xtargets='8:10;26:1' status='man'/>
</linkGrp>
